mocap_desktop_gui/__init__.py
mocap_desktop_gui/axengine_1766068856_3947648063.py
mocap_desktop_gui/gen/__init__.py
mocap_desktop_gui/gen/rc_icons.py
mocap_desktop_gui/gen/rc_qml.py
mocap_desktop_gui/gen/rc_style.py
mocap_desktop_gui/main.py
mocap_desktop_gui/mc/__init__.py
mocap_desktop_gui/mc/bld_fbx_2_glb.py
mocap_desktop_gui/mc/bld_utils.py
mocap_desktop_gui/mc/cm_license/AccessHandler.py
mocap_desktop_gui/mc/cm_license/LicenseCheck.py
mocap_desktop_gui/mc/cm_license/ListProductItem.py
mocap_desktop_gui/mc/gpu_info.py
mocap_desktop_gui/mc/mc_actor_profile.py
mocap_desktop_gui/mc/mc_actor_profile_model.py
mocap_desktop_gui/mc/mc_app_manager.py
mocap_desktop_gui/mc/mc_auth_core.py
mocap_desktop_gui/mc/mc_calib.py
mocap_desktop_gui/mc/mc_calib_data.py
mocap_desktop_gui/mc/mc_camera_views_model.py
mocap_desktop_gui/mc/mc_cloud_service.py
mocap_desktop_gui/mc/mc_common_paths.py
mocap_desktop_gui/mc/mc_context.py
mocap_desktop_gui/mc/mc_diagnosis.py
mocap_desktop_gui/mc/mc_env_vars.py
mocap_desktop_gui/mc/mc_error_codes.py
mocap_desktop_gui/mc/mc_file_util.py
mocap_desktop_gui/mc/mc_import_folder.py
mocap_desktop_gui/mc/mc_intrinsic_cam_models.py
mocap_desktop_gui/mc/mc_mocap_edit_session.py
mocap_desktop_gui/mc/mc_mocap_models.py
mocap_desktop_gui/mc/mc_project.py
mocap_desktop_gui/mc/mc_project_manager.py
mocap_desktop_gui/mc/mc_qml_defines.py
mocap_desktop_gui/mc/mc_rig.py
mocap_desktop_gui/mc/mc_scene_3d_service.py
mocap_desktop_gui/mc/mc_sync_media_player.py
mocap_desktop_gui/mc/mc_sync_video_decoder_service.py
mocap_desktop_gui/mc/mc_sync_video_paint_item.py
mocap_desktop_gui/mc/mc_take.py
mocap_desktop_gui/mc/mc_take_cloud_job.py
mocap_desktop_gui/mc/mc_take_cloud_job_action.py
mocap_desktop_gui/mc/mc_take_cloud_job_calib.py
mocap_desktop_gui/mc/mc_take_list_model.py
mocap_desktop_gui/mc/mc_take_local_job.py
mocap_desktop_gui/mc/mc_take_local_job_action.py
mocap_desktop_gui/mc/mc_take_local_job_calib.py
mocap_desktop_gui/mc/mc_take_local_job_service.py
mocap_desktop_gui-2.4.24.dist-info/METADATA
mocap_desktop_gui-2.4.24.dist-info/WHEEL
mocap_desktop_gui-2.4.24.dist-info/entry_points.txt
mocap_desktop_gui-2.4.24.dist-info/RECORD
