Metadata-Version: 2.1
Name: mocap-desktop-gui
Version: 2.4.24
Summary: 
Author: Move.ai
Requires-Python: >=3.10,<3.13
Classifier: Programming Language :: Python :: 3
Classifier: Programming Language :: Python :: 3.10
Classifier: Programming Language :: Python :: 3.11
Classifier: Programming Language :: Python :: 3.12
Requires-Dist: PySide6 (==6.8.1)
Requires-Dist: auth0-python (>=4.7.2,<5.0.0)
Requires-Dist: codemeter-api (>=8.30.500,<9.0.0)
Requires-Dist: h5py (>=3.8.0,<4.0.0)
Requires-Dist: move-ugc-python (>=3.0.0)
Requires-Dist: numpy (==1.26.0)
Requires-Dist: opencv-python (==4.10.0.84)
Requires-Dist: psutil (>=6.0.0,<7.0.0)
Requires-Dist: ruamel-yaml (>=0.18.6,<0.19.0)
Requires-Dist: typer (>=0.12.5,<0.13.0)
